{"type":"FeatureCollection","name":"demand_有完善消防设施需求的小区","crs":{"type":"name","properties":{"name":"urn:ogc:def:crs:OGC:1.3:CRS84"}},"features":[{"type":"Feature","properties":{},"geometry":{"type":"Point","coordinates":[108.34093440047607,22.81532072442256]}},{"type":"Feature","properties":{},"geometry":{"type":"Point","coordinates":[108.32659427793791,22.811594296278802]}},{"type":"Feature","properties":{},"geometry":{"type":"Point","coordinates":[108.33300054432237,22.80982635143318]}},{"type":"Feature","properties":{},"geometry":{"type":"Point","coordinates":[108.34106110311485,22.814318211316685]}},{"type":"Feature","properties":{},"geometry":{"type":"Point","coordinates":[108.33452281858703,22.814922950393022]}},{"type":"Feature","properties":{},"geometry":{"type":"Point","coordinates":[108.33460734282173,22.80885155122597]}},{"type":"Feature","properties":{},"geometry":{"type":"Point","coordinates":[108.32869648399438,22.81041787787976]}},{"type":"Feature","properties":{},"geometry":{"type":"Point","coordinates":[108.32520216655065,22.806942851580803]}},{"type":"Feature","properties":{},"geometry":{"type":"Point","coordinates":[108.32546767529954,22.814352465244276]}},{"type":"Feature","properties":{},"geometry":{"type":"Point","coordinates":[108.32755610574421,22.812288019439332]}},{"type":"Feature","properties":{},"geometry":{"type":"Point","coordinates":[108.32510532844422,22.810582650256073]}},{"type":"Feature","properties":{},"geometry":{"type":"Point","coordinates":[108.33466408289586,22.81398648605525]}},{"type":"Feature","properties":{},"geometry":{"type":"Point","coordinates":[108.33175448919518,22.81358324313383]}},{"type":"Feature","properties":{},"geometry":{"type":"Point","coordinates":[108.33350934097513,22.81450184380833]}},{"type":"Feature","properties":{},"geometry":{"type":"Point","coordinates":[108.33480693479603,22.814448807758346]}},{"type":"Feature","properties":{},"geometry":{"type":"Point","coordinates":[108.3363966407155,22.80815074461874]}},{"type":"Feature","properties":{},"geometry":{"type":"Point","coordinates":[108.33006767071078,22.812929093528908]}},{"type":"Feature","properties":{},"geometry":{"type":"Point","coordinates":[108.32731049069224,22.80913083794682]}},{"type":"Feature","properties":{},"geometry":{"type":"Point","coordinates":[108.34046179844039,22.81428599421032]}},{"type":"Feature","properties":{},"geometry":{"type":"Point","coordinates":[108.34449471621448,22.815223441589122]}},{"type":"Feature","properties":{},"geometry":{"type":"Point","coordinates":[108.34391851625595,22.813217107564654]}},{"type":"Feature","properties":{},"geometry":{"type":"Point","coordinates":[108.33201770486289,22.804868572710074]}},{"type":"Feature","properties":{},"geometry":{"type":"Point","coordinates":[108.32608430745672,22.81222718988536]}},{"type":"Feature","properties":{},"geometry":{"type":"Point","coordinates":[108.33434674668963,22.813821614307653]}},{"type":"Feature","properties":{},"geometry":{"type":"Point","coordinates":[108.3341309449578,22.814606980532478]}},{"type":"Feature","properties":{},"geometry":{"type":"Point","coordinates":[108.34222523108664,22.814403088837295]}},{"type":"Feature","properties":{},"geometry":{"type":"Point","coordinates":[108.33940129714716,22.815258580860228]}}]}