{"type":"FeatureCollection","name":"demand_有新增汽车停车位需求的小区","crs":{"type":"name","properties":{"name":"urn:ogc:def:crs:OGC:1.3:CRS84"}},"features":[{"type":"Feature","properties":{},"geometry":{"type":"Point","coordinates":[108.34100715457654,22.815319302786705]}},{"type":"Feature","properties":{},"geometry":{"type":"Point","coordinates":[108.33457802443398,22.814924140247758]}},{"type":"Feature","properties":{},"geometry":{"type":"Point","coordinates":[108.33823914871758,22.808234019449486]}},{"type":"Feature","properties":{},"geometry":{"type":"Point","coordinates":[108.32875627166335,22.810417396103606]}},{"type":"Feature","properties":{},"geometry":{"type":"Point","coordinates":[108.32532103772058,22.806944799736527]}},{"type":"Feature","properties":{},"geometry":{"type":"Point","coordinates":[108.32497744883428,22.81422600333914]}},{"type":"Feature","properties":{},"geometry":{"type":"Point","coordinates":[108.33473156466559,22.8139698593046]}},{"type":"Feature","properties":{},"geometry":{"type":"Point","coordinates":[108.33065460235727,22.80912093276577]}},{"type":"Feature","properties":{},"geometry":{"type":"Point","coordinates":[108.33349054264326,22.814895542324834]}},{"type":"Feature","properties":{},"geometry":{"type":"Point","coordinates":[108.33447497091689,22.814340982934258]}},{"type":"Feature","properties":{},"geometry":{"type":"Point","coordinates":[108.3364922422361,22.808147675860432]}},{"type":"Feature","properties":{},"geometry":{"type":"Point","coordinates":[108.33022156164843,22.81292356452027]}},{"type":"Feature","properties":{},"geometry":{"type":"Point","coordinates":[108.33223772698506,22.804864502418074]}},{"type":"Feature","properties":{},"geometry":{"type":"Point","coordinates":[108.33439523763943,22.81381709243212]}},{"type":"Feature","properties":{},"geometry":{"type":"Point","coordinates":[108.33370095210246,22.81415890836681]}},{"type":"Feature","properties":{},"geometry":{"type":"Point","coordinates":[108.33564967191747,22.8079787147422]}},{"type":"Feature","properties":{},"geometry":{"type":"Point","coordinates":[108.34238354391009,22.814401692349946]}},{"type":"Feature","properties":{},"geometry":{"type":"Point","coordinates":[108.34932422434161,22.813406031885464]}}]}