{"type":"FeatureCollection","name":"problem_存在易涝积水点的城中村自建房区域_点","crs":{"type":"name","properties":{"name":"urn:ogc:def:crs:OGC:1.3:CRS84"}},"features":[{"type":"Feature","properties":{"所在社区":"纬武社区","所在市":"南宁市","所在县区":"青秀区","所在街道":"新竹街道办","小区名称":"花市","ORIG_FID":1},"geometry":{"type":"Point","coordinates":[108.32763659589325,22.81173987010009]}},{"type":"Feature","properties":{"所在社区":"大板三社区南","所在市":"南宁市","所在县区":"青秀区","所在街道":"津头街道办","小区名称":"南湖村","ORIG_FID":2},"geometry":{"type":"Point","coordinates":[108.33795503700863,22.80667999195515]}},{"type":"Feature","properties":{"所在社区":"大板三社区南","所在市":"南宁市","所在县区":"青秀区","所在街道":"津头街道办","小区名称":"南湖村","ORIG_FID":3},"geometry":{"type":"Point","coordinates":[108.33839880587665,22.807675106547276]}},{"type":"Feature","properties":{"所在社区":"大板三社区南","所在市":"南宁市","所在县区":"青秀区","所在街道":"津头街道办","小区名称":"南湖村","ORIG_FID":4},"geometry":{"type":"Point","coordinates":[108.3375491385209,22.806496212965737]}},{"type":"Feature","properties":{"所在社区":"大板三社区南","所在市":"南宁市","所在县区":"青秀区","所在街道":"津头街道办","小区名称":"南湖村","ORIG_FID":5},"geometry":{"type":"Point","coordinates":[108.33807316695298,22.806182170883414]}},{"type":"Feature","properties":{"所在社区":"大板三社区南","所在市":"南宁市","所在县区":"青秀区","所在街道":"津头街道办","小区名称":"南湖村","ORIG_FID":6},"geometry":{"type":"Point","coordinates":[108.33880491687583,22.806677622014618]}},{"type":"Feature","properties":{"所在社区":"纬武社区","所在市":"南宁市","所在县区":"青秀区","所在街道":"新竹街道办","小区名称":"纬武社区自建房","ORIG_FID":7},"geometry":{"type":"Point","coordinates":[108.32717276112517,22.814349481961237]}}]}