{"type":"FeatureCollection","name":"problem_公园绿化活动场地服务半径未覆盖的小区_点","crs":{"type":"name","properties":{"name":"urn:ogc:def:crs:OGC:1.3:CRS84"}},"features":[{"type":"Feature","properties":{"Id":0,"问题":"公园绿化活动场地未覆盖的小区","ORIG_FID":1},"geometry":{"type":"Point","coordinates":[108.3330954307984,22.809861979497015]}},{"type":"Feature","properties":{"Id":0,"问题":"公园绿化活动场地未覆盖的小区","ORIG_FID":2},"geometry":{"type":"Point","coordinates":[108.33506013889581,22.8101363690776]}},{"type":"Feature","properties":{"Id":0,"问题":"公园绿化活动场地未覆盖的小区","ORIG_FID":3},"geometry":{"type":"Point","coordinates":[108.33489599773351,22.810132324530542]}},{"type":"Feature","properties":{"Id":0,"问题":"公园绿化活动场地未覆盖的小区","ORIG_FID":4},"geometry":{"type":"Point","coordinates":[108.33009110786725,22.805456089143963]}},{"type":"Feature","properties":{"Id":0,"问题":"公园绿化活动场地未覆盖的小区","ORIG_FID":5},"geometry":{"type":"Point","coordinates":[108.32909177026536,22.804647476699092]}},{"type":"Feature","properties":{"Id":0,"问题":"公园绿化活动场地未覆盖的小区","ORIG_FID":6},"geometry":{"type":"Point","coordinates":[108.32757284115193,22.805029459721588]}},{"type":"Feature","properties":{"Id":0,"问题":"公园绿化活动场地未覆盖的小区","ORIG_FID":7},"geometry":{"type":"Point","coordinates":[108.32714605521747,22.807205047814413]}},{"type":"Feature","properties":{"Id":0,"问题":"公园绿化活动场地未覆盖的小区","ORIG_FID":8},"geometry":{"type":"Point","coordinates":[108.32786030228505,22.807267933448443]}},{"type":"Feature","properties":{"Id":0,"问题":"公园绿化活动场地未覆盖的小区","ORIG_FID":9},"geometry":{"type":"Point","coordinates":[108.32751440086317,22.807659773008705]}},{"type":"Feature","properties":{"Id":0,"问题":"公园绿化活动场地未覆盖的小区","ORIG_FID":10},"geometry":{"type":"Point","coordinates":[108.32679896976846,22.808836106896624]}},{"type":"Feature","properties":{"Id":0,"问题":"公园绿化活动场地未覆盖的小区","ORIG_FID":11},"geometry":{"type":"Point","coordinates":[108.32997867265135,22.804113758834934]}},{"type":"Feature","properties":{"Id":0,"问题":"公园绿化活动场地未覆盖的小区","ORIG_FID":12},"geometry":{"type":"Point","coordinates":[108.32761608543902,22.805384768977934]}},{"type":"Feature","properties":{"Id":0,"问题":"公园绿化活动场地未覆盖的小区","ORIG_FID":13},"geometry":{"type":"Point","coordinates":[108.32988593444678,22.80547887193661]}},{"type":"Feature","properties":{"Id":0,"问题":"公园绿化活动场地未覆盖的小区","ORIG_FID":14},"geometry":{"type":"Point","coordinates":[108.32878517384543,22.805751510450992]}},{"type":"Feature","properties":{"Id":0,"问题":"公园绿化活动场地未覆盖的小区","ORIG_FID":15},"geometry":{"type":"Point","coordinates":[108.32734322081448,22.806743253345406]}},{"type":"Feature","properties":{"Id":0,"问题":"公园绿化活动场地未覆盖的小区","ORIG_FID":16},"geometry":{"type":"Point","coordinates":[108.32649026659674,22.806322471067947]}},{"type":"Feature","properties":{"Id":0,"问题":"公园绿化活动场地未覆盖的小区","ORIG_FID":17},"geometry":{"type":"Point","coordinates":[108.32540130776863,22.806981876345585]}},{"type":"Feature","properties":{"Id":0,"问题":"公园绿化活动场地未覆盖的小区","ORIG_FID":18},"geometry":{"type":"Point","coordinates":[108.32441379695614,22.807169736013993]}},{"type":"Feature","properties":{"Id":0,"问题":"公园绿化活动场地未覆盖的小区","ORIG_FID":19},"geometry":{"type":"Point","coordinates":[108.32739970764128,22.808448705010083]}},{"type":"Feature","properties":{"Id":0,"问题":"公园绿化活动场地未覆盖的小区","ORIG_FID":20},"geometry":{"type":"Point","coordinates":[108.3285855349485,22.8081513680535]}},{"type":"Feature","properties":{"Id":0,"问题":"公园绿化活动场地未覆盖的小区","ORIG_FID":21},"geometry":{"type":"Point","coordinates":[108.32919878887182,22.809120227979534]}},{"type":"Feature","properties":{"Id":0,"问题":"公园绿化活动场地未覆盖的小区","ORIG_FID":22},"geometry":{"type":"Point","coordinates":[108.32709106116782,22.80922249528899]}},{"type":"Feature","properties":{"Id":0,"问题":"公园绿化活动场地未覆盖的小区","ORIG_FID":23},"geometry":{"type":"Point","coordinates":[108.32829591094485,22.806880786421573]}},{"type":"Feature","properties":{"Id":0,"问题":"公园绿化活动场地未覆盖的小区","ORIG_FID":24},"geometry":{"type":"Point","coordinates":[108.32739177168104,22.807743581699327]}},{"type":"Feature","properties":{"Id":0,"问题":"公园绿化活动场地未覆盖的小区","ORIG_FID":25},"geometry":{"type":"Point","coordinates":[108.32696068959692,22.808062469535823]}},{"type":"Feature","properties":{"Id":0,"问题":"公园绿化活动场地未覆盖的小区","ORIG_FID":26},"geometry":{"type":"Point","coordinates":[108.33003939036195,22.806971301452936]}}]}